pytest_docker_py/__init__.py
pytest_docker_py/config.py
pytest_docker_py/docker_py_wrapper.py
pytest_docker_py/plugin.py
pytest_docker_py-1.1.3.dist-info/LICENSE
pytest_docker_py-1.1.3.dist-info/METADATA
pytest_docker_py-1.1.3.dist-info/WHEEL
pytest_docker_py-1.1.3.dist-info/entry_points.txt
pytest_docker_py-1.1.3.dist-info/top_level.txt
pytest_docker_py-1.1.3.dist-info/RECORD
