Metadata-Version: 2.1
Name: pytest-docker-py
Version: 1.1.3
Summary: Easy to use, simple to extend, pytest plugin that minimally leverages docker-py.
Home-page: https://github.com/jameshnsears/pytest-docker-py
Author: James Sears
Author-email: james.hn.sears@gmail.com
License: Apache 2.0
Keywords: pytest plugin docker-py
Platform: UNKNOWN
Classifier: Framework :: Pytest
Classifier: Programming Language :: Python :: 3.6
Classifier: Topic :: Software Development :: Testing
Classifier: Intended Audience :: Developers
Classifier: License :: OSI Approved :: Apache Software License
Requires-Dist: pytest (==4.0.0)
Requires-Dist: docker (==3.5.1)
